wuyi/__init__.py
wuyi/__main__.py
wuyi/clustering/kmeans.py
wuyi/core/distances.py
wuyi/core/tf-idf.py
wuyi/metric/BLEU.py
wuyi/metric/ROUGE.py
wuyi/metric/rouge_score.py
wuyi/tokenizers/BasicTokenizer.py
WuYi-0.0.6.dist-info/LICENSE
WuYi-0.0.6.dist-info/METADATA
WuYi-0.0.6.dist-info/WHEEL
WuYi-0.0.6.dist-info/top_level.txt
WuYi-0.0.6.dist-info/RECORD
