Metadata-Version: 2.1
Name: WuYi
Version: 0.0.6
Summary: A small NLP tool package.
Home-page: https://github.com/Moriarty12138/WuYi
Author: Jia Guoqing
Author-email: jiaguoqing12138@gmail.com
License: UNKNOWN
Project-URL: Bug Tracker, https://github.com/Moriarty12138/WuYi/issues
Platform: UNKNOWN
Classifier: Programming Language :: Python :: 3
Classifier: License :: OSI Approved :: MIT License
Classifier: Operating System :: OS Independent
Requires-Python: >=3.6
